lndb_schema_bionty/__init__.py
lndb_schema_bionty/_core.py
lndb_schema_bionty-0.2.0.dist-info/LICENSE
lndb_schema_bionty-0.2.0.dist-info/WHEEL
lndb_schema_bionty-0.2.0.dist-info/METADATA
lndb_schema_bionty-0.2.0.dist-info/RECORD
