Metadata-Version: 2.1
Name: lndb_schema_bionty
Version: 0.2.0
Summary: Biological entities schema module.
Author-email: Lamin Labs <laminlabs@gmail.com>
Requires-Dist: nbproject
Requires-Dist: sqlmodel
Requires-Dist: pre-commit ; extra == "dev"
Requires-Dist: nox ; extra == "dev"
Requires-Dist: pytest>=6.0 ; extra == "test"
Requires-Dist: pytest-cov ; extra == "test"
Project-URL: Home, https://github.com/laminlabs/lndb-schema-bionty
Provides-Extra: dev
Provides-Extra: test
